Metadata-Version: 1.0
Name: django-microservices
Version: 0.1
Summary: A framework for building microservices with Django.
Home-page: https://github.com/lander2k2/django-microservices
Author: Richard Lander
Author-email: lander2k2@gmail.com
License: MIT
Platform: UNKNOWN
